tensorpac/__init__.py
tensorpac/config.py
tensorpac/gcmi.py
tensorpac/io.py
tensorpac/pac.py
tensorpac/signals.py
tensorpac/spectral.py
tensorpac/stats.py
tensorpac/utils.py
tensorpac/visu.py
tensorpac/__pycache__/__init__.cpython-37.pyc
tensorpac/__pycache__/config.cpython-37.pyc
tensorpac/__pycache__/gcmi.cpython-37.pyc
tensorpac/__pycache__/io.cpython-37.pyc
tensorpac/__pycache__/pac.cpython-37.pyc
tensorpac/__pycache__/signals.cpython-37.pyc
tensorpac/__pycache__/spectral.cpython-37.pyc
tensorpac/__pycache__/stats.cpython-37.pyc
tensorpac/__pycache__/utils.cpython-37.pyc
tensorpac/__pycache__/visu.cpython-37.pyc
tensorpac/methods/__init__.py
tensorpac/methods/meth_erpac.py
tensorpac/methods/meth_pac.py
tensorpac/methods/meth_pac_nb.py
tensorpac/methods/meth_pp.py
tensorpac/methods/meth_surrogates.py
tensorpac/methods/meth_switch.py
tensorpac/methods/__pycache__/__init__.cpython-37.pyc
tensorpac/methods/__pycache__/meth_erpac.cpython-37.pyc
tensorpac/methods/__pycache__/meth_pac.cpython-37.pyc
tensorpac/methods/__pycache__/meth_pac_nb._kl_hr_nb-58.py37m.1.nbc
tensorpac/methods/__pycache__/meth_pac_nb._kl_hr_nb-58.py37m.nbi
tensorpac/methods/__pycache__/meth_pac_nb.cpython-37.pyc
tensorpac/methods/__pycache__/meth_pac_nb.heights_ratio_nb-132.py37m.1.nbc
tensorpac/methods/__pycache__/meth_pac_nb.heights_ratio_nb-132.py37m.nbi
tensorpac/methods/__pycache__/meth_pac_nb.mean_vector_length_nb-21.py37m.1.nbc
tensorpac/methods/__pycache__/meth_pac_nb.mean_vector_length_nb-21.py37m.nbi
tensorpac/methods/__pycache__/meth_pac_nb.modulation_index_nb-80.py37m.1.nbc
tensorpac/methods/__pycache__/meth_pac_nb.modulation_index_nb-80.py37m.nbi
tensorpac/methods/__pycache__/meth_pp.cpython-37.pyc
tensorpac/methods/__pycache__/meth_surrogates.cpython-37.pyc
tensorpac/methods/__pycache__/meth_switch.cpython-37.pyc
tensorpac/methods/tests/test_pac_methods.py
tensorpac/methods/tests/__pycache__/test_pac_methods.cpython-37-PYTEST.pyc
tensorpac-0.6.5.dist-info/LICENSE
tensorpac-0.6.5.dist-info/METADATA
tensorpac-0.6.5.dist-info/WHEEL
tensorpac-0.6.5.dist-info/top_level.txt
tensorpac-0.6.5.dist-info/RECORD
