Metadata-Version: 1.2
Name: tensorpac
Version: 0.6.5
Summary: Tensor-based Phase-Amplitude Coupling
Home-page: http://etiennecmb.github.io/tensorpac/
Author: Etienne Combrisson
Author-email: e.combrisson@gmail.com
Maintainer: Etienne Combrisson
License: BSD 3-Clause License
Download-URL: https://github.com/EtienneCmb/tensorpac/archive/v0.6.5.tar.gz
Keywords: phase-amplitude coupling pac tensor oscillation meg eeg python
Platform: any
Classifier: Development Status :: 5 - Production/Stable
Classifier: Intended Audience :: Science/Research
Classifier: Intended Audience :: Education
Classifier: Intended Audience :: Developers
Classifier: Programming Language :: Python :: 3.6
Classifier: Programming Language :: Python :: 3.7
Classifier: Programming Language :: Python :: 3.7
